autotweet/__init__.py
autotweet/command.py
autotweet/compat.py
autotweet/daemons.py
autotweet/database.py
autotweet/learning.py
autotweet/logger_factory.py
autotweet/telegram_bot.py
autotweet/twitter.py
autotweet-0.5.3.dist-info/DESCRIPTION.rst
autotweet-0.5.3.dist-info/METADATA
autotweet-0.5.3.dist-info/RECORD
autotweet-0.5.3.dist-info/WHEEL
autotweet-0.5.3.dist-info/entry_points.txt
autotweet-0.5.3.dist-info/metadata.json
autotweet-0.5.3.dist-info/top_level.txt
