Metadata-Version: 2.0
Name: autotweet
Version: 0.5.3
Summary: learn your tweet and auto tweet it.
Home-page: https://github.com/Kjwon15/autotweet/
Author: Kjwon15
Author-email: kjwonmail@gmail.com
License: MIT
Download-URL: https://github.com/Kjwon15/autotweet/releases
Platform: UNKNOWN
Classifier: Development Status :: 5 - Production/Stable
Classifier: Environment :: Console
Classifier: Environment :: No Input/Output (Daemon)
Classifier: License :: OSI Approved :: MIT License
Classifier: Operating System :: OS Independent
Classifier: Programming Language :: Python
Classifier: Programming Language :: Python :: 2
Classifier: Programming Language :: Python :: 3
Classifier: Topic :: Communications :: Chat
Classifier: Topic :: Utilities
Requires-Dist: sqlalchemy (>=0.9.6)
Requires-Dist: tweepy (>=2.3.0)
Provides-Extra: telegram
Requires-Dist: python-telegram-bot (>=5.2.0); extra == 'telegram'
